drupal_download/__init__.py
drupal_download/__main__.py
drupal_download/downloader.py
drupal_download/tests/__init__.py
drupal_download/tests/file_dumper.py
drupal_download/tests/test_downloader.py
drupal_download-0.0.3.dist-info/LICENSE
drupal_download-0.0.3.dist-info/METADATA
drupal_download-0.0.3.dist-info/WHEEL
drupal_download-0.0.3.dist-info/top_level.txt
drupal_download-0.0.3.dist-info/RECORD
