Metadata-Version: 2.1
Name: drupal-download
Version: 0.0.3
Summary: Download data from Drupal using Python
Home-page: https://github.com/zelenij/python-drupal-download
Author: Andre Bar'yudin
Author-email: andre.baryudin@gmail.com
License: MIT
Keywords: drupal download data migration wagtail
Platform: UNKNOWN
Classifier: Development Status :: 3 - Alpha
Classifier: License :: OSI Approved :: MIT License
Classifier: Programming Language :: Python :: 3
Classifier: Topic :: Internet
Requires-Python: >=3.6
